node_soso/__init__.py
node_soso/xmldump.py
node_soso-1.3.0.dist-info/entry_points.txt
node_soso-1.3.0.dist-info/licenses/LICENSE
node_soso-1.3.0.dist-info/WHEEL
node_soso-1.3.0.dist-info/METADATA
node_soso-1.3.0.dist-info/RECORD
