Metadata-Version: 2.4
Name: node_soso
Version: 1.3.0
Summary: XML enhancements to make a few things easier.
Author-email: Leon Dionne <ldionne@dridesign.sh.cn>
Classifier: License :: OSI Approved :: GNU General Public License v3 or later (GPLv3+)
Classifier: Programming Language :: Python
Classifier: Programming Language :: Python :: 3.10
Classifier: Topic :: Utilities
License-File: LICENSE
Project-URL: Home, https://github.com/Zen-Master-SoSo/node_soso
